diagrambot/__init__.py
diagrambot/__main__.py
diagrambot/cli.py
diagrambot/diagrambot.py
diagrambot/utils.py
diagrambot-0.1.0.dist-info/licenses/LICENSE
diagrambot-0.1.0.dist-info/METADATA
diagrambot-0.1.0.dist-info/WHEEL
diagrambot-0.1.0.dist-info/entry_points.txt
diagrambot-0.1.0.dist-info/top_level.txt
diagrambot-0.1.0.dist-info/RECORD
